room_with_a_view/__init__.py
room_with_a_view/cli.py
room_with_a_view/room_with_a_view.py
room_with_a_view-0.1.6.dist-info/licenses/AUTHORS.rst
room_with_a_view-0.1.6.dist-info/licenses/LICENSE
room_with_a_view-0.1.6.dist-info/METADATA
room_with_a_view-0.1.6.dist-info/WHEEL
room_with_a_view-0.1.6.dist-info/entry_points.txt
room_with_a_view-0.1.6.dist-info/top_level.txt
room_with_a_view-0.1.6.dist-info/RECORD
