Metadata-Version: 2.4
Name: room_with_a_view
Version: 0.1.6
Summary: View management for Amazon's Redshift
Home-page: https://github.com/b12io/room_with_a_view
Author: Unlimited Labs, Inc.
Author-email: hello@b12.io
License: Apache Software License 2.0
Keywords: room_with_a_view
Classifier: Development Status :: 2 - Pre-Alpha
Classifier: Intended Audience :: Developers
Classifier: License :: OSI Approved :: Apache Software License
Classifier: Natural Language :: English
Classifier: Programming Language :: Python :: 3
Classifier: Programming Language :: Python :: 3.4
Classifier: Programming Language :: Python :: 3.5
Classifier: Programming Language :: Python :: 3.6
License-File: LICENSE
License-File: AUTHORS.rst
Requires-Dist: psycopg2==2.9.9
Requires-Dist: PyYAML==6.0.1
Dynamic: author
Dynamic: author-email
Dynamic: classifier
Dynamic: description
Dynamic: home-page
Dynamic: keywords
Dynamic: license
Dynamic: license-file
Dynamic: requires-dist
Dynamic: summary
